ImageEffects
resources
