Metadata-Version: 2.1
Name: ImageEffects
Version: 0.0.2
Summary: A library to add effects to your images.
Home-page: https://github.com/prashantrahul141/ImageEffects
Author: prashantrahul141
License: MIT
Keywords: python,image,manipulation,pillow,PIL
Platform: unix
Platform: linux
Platform: osx
Platform: cygwin
Platform: win32
Classifier: Programming Language :: Python :: 3
Classifier: Programming Language :: Python :: 3 :: Only
Classifier: Programming Language :: Python :: 3.6
Classifier: Programming Language :: Python :: 3.7
Classifier: Programming Language :: Python :: 3.8
Classifier: Programming Language :: Python :: 3.9
Classifier: Operating System :: OS Independent
Classifier: License :: OSI Approved :: MIT License
Requires-Python: >=3.6
License-File: LICENSE
Requires-Dist: Pillow (>=9.3.0)
Requires-Dist: art (>=5.8)
Requires-Dist: numpy (>=1.24.0)
